README.txt
setup.py
mytestlib/__init__.py
mytestlib/greet.py
mytestlibrary1990.egg-info/PKG-INFO
mytestlibrary1990.egg-info/SOURCES.txt
mytestlibrary1990.egg-info/dependency_links.txt
mytestlibrary1990.egg-info/top_level.txt