Metadata-Version: 1.0
Name: mytestlibrary1990
Version: 1.0.0
Summary: My Test Library.
Home-page: UNKNOWN
Author: AA
Author-email: a-andou@kbsanhe.co.jp
License: UNKNOWN
Platform: UNKNOWN
